<?xml version="1.0" encoding="utf-8" ?>
<dwsync>
<file name="index_media.htm" server="bundang.leadersacademy.com//home/skin/skin020/mobile/" local="131608531800000000" remote="131608531800000000" Dst="1" />
<file name="item_1.htm" server="bundang.leadersacademy.com//home/skin/skin020/mobile/" local="131608531800000000" remote="131608531800000000" Dst="1" />
<file name="item_10.htm" server="bundang.leadersacademy.com//home/skin/skin020/mobile/" local="131608531800000000" remote="131608531800000000" Dst="1" />
<file name="item_11.htm" server="bundang.leadersacademy.com//home/skin/skin020/mobile/" local="131608531800000000" remote="131608531800000000" Dst="1" />
<file name="item_12.htm" server="bundang.leadersacademy.com//home/skin/skin020/mobile/" local="131608531800000000" remote="131608531800000000" Dst="1" />
<file name="item_13.htm" server="bundang.leadersacademy.com//home/skin/skin020/mobile/" local="131608531800000000" remote="131608531800000000" Dst="1" />
<file name="item_14.htm" server="bundang.leadersacademy.com//home/skin/skin020/mobile/" local="131608531800000000" remote="131608531800000000" Dst="1" />
<file name="item_15.htm" server="bundang.leadersacademy.com//home/skin/skin020/mobile/" local="131608531800000000" remote="131608531800000000" Dst="1" />
<file name="item_2.htm" server="bundang.leadersacademy.com//home/skin/skin020/mobile/" local="131608531800000000" remote="131608531800000000" Dst="1" />
<file name="item_3.htm" server="bundang.leadersacademy.com//home/skin/skin020/mobile/" local="131608531800000000" remote="131608531800000000" Dst="1" />
<file name="item_4.htm" server="bundang.leadersacademy.com//home/skin/skin020/mobile/" local="131608531800000000" remote="131608531800000000" Dst="1" />
<file name="item_5.htm" server="bundang.leadersacademy.com//home/skin/skin020/mobile/" local="131608531800000000" remote="131608531800000000" Dst="1" />
<file name="item_6.htm" server="bundang.leadersacademy.com//home/skin/skin020/mobile/" local="131608531800000000" remote="131608531800000000" Dst="1" />
<file name="item_7.htm" server="bundang.leadersacademy.com//home/skin/skin020/mobile/" local="131608531800000000" remote="131608531800000000" Dst="1" />
<file name="item_8.htm" server="bundang.leadersacademy.com//home/skin/skin020/mobile/" local="131608531800000000" remote="131608531800000000" Dst="1" />
<file name="item_9.htm" server="bundang.leadersacademy.com//home/skin/skin020/mobile/" local="131608531800000000" remote="131608531800000000" Dst="1" />
<file name="media.htm" server="bundang.leadersacademy.com//home/skin/skin020/mobile/" local="131591874600000000" remote="131591874600000000" Dst="1" />
</dwsync>